cron_wrapper-0.1.3.dist-info/licenses/LICENSE
cronwrapper/__init__.py
cronwrapper/cronwrap.py
cron_wrapper-0.1.3.dist-info/METADATA
cron_wrapper-0.1.3.dist-info/WHEEL
cron_wrapper-0.1.3.dist-info/entry_points.txt
cron_wrapper-0.1.3.dist-info/top_level.txt
cron_wrapper-0.1.3.dist-info/RECORD
